tagtools/__init__.py
tagtools/apps.py
tagtools/models.py
tagtools/settings.py
tagtools/tagcloud.py
tagtools/tools.py
tagtools/views.py
tagtools/management/__init__.py
tagtools/management/commands/__init__.py
tagtools/management/commands/migrate_tagging_to_taggit.py
django_tag_tools-0.4.0.dist-info/WHEEL
django_tag_tools-0.4.0.dist-info/METADATA
django_tag_tools-0.4.0.dist-info/RECORD
